{
    "Layout_2026-05-24_19-07-16": {
        "icons": {
            "nahid": {
                "x": 1840,
                "y": 802
            },
            "This PC": {
                "x": 16,
                "y": 102
            },
            "Recycle Bin": {
                "x": 16,
                "y": 202
            },
            "Control Panel": {
                "x": 16,
                "y": 302
            },
            "DesktopOK": {
                "x": 16,
                "y": 402
            },
            "Google Chrome": {
                "x": 16,
                "y": 502
            },
            "PotPlayer 64 bit": {
                "x": 16,
                "y": 602
            },
            "Sonarr": {
                "x": 16,
                "y": 702
            },
            "Prowlarr": {
                "x": 16,
                "y": 802
            },
            "Cleanuparr": {
                "x": 16,
                "y": 902
            },
            "UniGetUI": {
                "x": 92,
                "y": 2
            },
            "Zoom Workplace": {
                "x": 92,
                "y": 102
            },
            "Sniffnet": {
                "x": 92,
                "y": 202
            },
            "Thunderbird": {
                "x": 92,
                "y": 302
            },
            "QuickLook": {
                "x": 92,
                "y": 402
            },
            "Free Download Manager": {
                "x": 92,
                "y": 502
            },
            "Xodo PDF Reader": {
                "x": 92,
                "y": 602
            },
            "BCUninstaller": {
                "x": 92,
                "y": 702
            },
            "Google": {
                "x": 92,
                "y": 802
            },
            "Helium": {
                "x": 92,
                "y": 902
            },
            "KDE Connect": {
                "x": 168,
                "y": 2
            },
            "NotebookLM": {
                "x": 168,
                "y": 102
            },
            "XLaunch": {
                "x": 168,
                "y": 202
            },
            "nexusfont": {
                "x": 168,
                "y": 302
            },
            "Google AI Studio": {
                "x": 168,
                "y": 402
            },
            "Nahid - Chrome": {
                "x": 168,
                "y": 502
            },
            "JDownloader 2": {
                "x": 168,
                "y": 602
            },
            "Excel-like Data Table": {
                "x": 168,
                "y": 702
            },
            "Analytical": {
                "x": 244,
                "y": 2
            },
            "SyncFolders": {
                "x": 244,
                "y": 302
            },
            "youtube-cookie.txt": {
                "x": 244,
                "y": 402
            },
            "art.7z": {
                "x": 244,
                "y": 502
            },
            "Excel-like Data Table.pdf": {
                "x": 244,
                "y": 602
            },
            "asdasdasdasd.txt": {
                "x": 244,
                "y": 702
            },
            "scientific_calculator": {
                "x": 244,
                "y": 802
            },
            "Taxes Zone-Noakhali - TAXNOA _ Powered By Teletalk.pdf": {
                "x": 244,
                "y": 902
            },
            "Islamic Foundation - IFB _ Powered By Teletalk.pdf": {
                "x": 320,
                "y": 102
            },
            "Gallery": {
                "x": 320,
                "y": 202
            },
            "Gas Transmission Company Limited (GTCL) - GTCL _ Powered By Teletalk.pdf": {
                "x": 320,
                "y": 302
            },
            "DOSBox 0.74-3": {
                "x": 320,
                "y": 402
            },
            "\u09eb\u09e6\u09a4\u09ae \u09ac\u09bf\u09b8\u09bf\u098f\u09b8 \u09b8\u09be\u09ae\u09cd\u09aa\u09cd\u09b0\u09a4\u09bf\u0995 \u0993 \u099a\u09b2\u09ae\u09be\u09a8 \u0998\u099f\u09a8\u09be  \u09aa\u09cd\u09b0\u09ac\u09be\u09b9 by Zahidul Islam BCS Intelligence.pdf": {
                "x": 928,
                "y": 102
            },
            "Vocab.txt": {
                "x": 928,
                "y": 302
            },
            "new 1.txt": {
                "x": 928,
                "y": 402
            },
            "481133401_1792295234890919_906037966534795884_n.jpg": {
                "x": 1004,
                "y": 2
            },
            "Map_of_Bangladesh-en.svg": {
                "x": 1004,
                "y": 102
            },
            "surakafirun.png": {
                "x": 1004,
                "y": 202
            },
            "@delta.xlsx": {
                "x": 1080,
                "y": 2
            },
            "xHTML.html": {
                "x": 1080,
                "y": 502
            },
            "New folder": {
                "x": 1232,
                "y": 402
            },
            "FB_Group_IMG": {
                "x": 1232,
                "y": 902
            },
            "math kiro": {
                "x": 1308,
                "y": 902
            },
            "image_403.png": {
                "x": 1384,
                "y": 602
            },
            "TEST": {
                "x": 1384,
                "y": 902
            },
            "song": {
                "x": 1460,
                "y": 902
            },
            "image_336.png": {
                "x": 1536,
                "y": 502
            },
            "ShareFolder": {
                "x": 1536,
                "y": 902
            },
            "admitcard": {
                "x": 1612,
                "y": 902
            },
            "msBackups": {
                "x": 1688,
                "y": 902
            },
            "playlist.dpl": {
                "x": 1764,
                "y": 802
            },
            "ms1": {
                "x": 1764,
                "y": 902
            },
            "myShare": {
                "x": 1840,
                "y": 502
            },
            "Root": {
                "x": 1840,
                "y": 602
            },
            "youtube_cookies.txt": {
                "x": 1840,
                "y": 702
            },
            "@JOB": {
                "x": 1840,
                "y": 902
            }
        },
        "windows": [
            {
                "title": "python",
                "class": "Qt6110QWindowToolSaveBits",
                "x": 60,
                "y": 990,
                "w": 1800,
                "h": 39
            },
            {
                "title": "CYBER_DESKTOP_OK v1.0",
                "class": "Qt6110QWindowIcon",
                "x": 702,
                "y": 185,
                "w": 516,
                "h": 639
            },
            {
                "title": "snipping tool video resolution - Google Search - Google Chrome",
                "class": "Chrome_WidgetWin_1",
                "x": -32000,
                "y": -32000,
                "w": 160,
                "h": 28
            },
            {
                "title": "Snipping Tool",
                "class": "XamlWindow",
                "x": -32000,
                "y": -32000,
                "w": 160,
                "h": 28
            },
            {
                "title": "snap_recording - File Explorer",
                "class": "CabinetWClass",
                "x": -32000,
                "y": -32000,
                "w": 160,
                "h": 28
            },
            {
                "title": "Zoom Workplace",
                "class": "ZPPTMainFrmWndClassEx",
                "x": -32000,
                "y": -32000,
                "w": 160,
                "h": 28
            },
            {
                "title": "Jackett",
                "class": "WindowsForms10.Window.8.app.0.784086_r3_ad1",
                "x": 0,
                "y": 1004,
                "w": 160,
                "h": 28
            },
            {
                "title": "Windows Input Experience",
                "class": "Windows.UI.Core.CoreWindow",
                "x": 0,
                "y": 0,
                "w": 1920,
                "h": 1080
            },
            {
                "title": "Program Manager",
                "class": "Progman",
                "x": 0,
                "y": 0,
                "w": 1920,
                "h": 1080
            }
        ]
    }
}